{
  "updated_at": 1725811801,
  "data": {
    "today": {
      "top_songs": [],
      "top_albums": [],
      "top_artists": [],
      "total_listen_time": []
    },
    "yesterday": {
      "top_songs": [],
      "top_albums": [],
      "top_artists": [],
      "total_listen_time": []
    },
    "week": {
      "top_songs": [],
      "top_albums": [],
      "top_artists": [],
      "total_listen_time": []
    },
    "month": {
      "top_songs": [
        {
          "_id": "5YzPYZKg94yEOgSlODzfK1",
          "count": 2,
          "details": {
            "id": "5YzPYZKg94yEOgSlODzfK1",
            "progress": 34.73122965317474,
            "duration_ms": 234066,
            "playing": true,
            "name": "\u30b2\u30b7\u30e5\u30bf\u30eb\u30c8 - \u5d29\u58caRemix",
            "preview_url": "https://p.scdn.co/mp3-preview/c7f5aa5a2f713adfff3cfed9ea73ed682b51039d?cid=ffce38f98386483bbbee2d4831104c2b",
            "artists": [
              {
                "name": "\u82b1\u8b5c",
                "id": "2c32JruIkUyfdycHmhIph4"
              },
              {
                "name": "Otome",
                "id": "6lDhtdOHuApMDkvQWtDpdV"
              }
            ],
            "context": {
              "external_urls": {
                "spotify": "https://open.spotify.com/collection/tracks"
              },
              "href": "https://api.spotify.com/v1/me/tracks",
              "type": "collection",
              "uri": "spotify:user:216m3lxuwmrmfde7wksjzb4pa:collection"
            },
            "album": {
              "name": "\u30b2\u30b7\u30e5\u30bf\u30eb\u30c8 (\u5d29\u58caRemix)",
              "id": "5hdH3H4sjF4OoGsTyzPTLI",
              "release_date": "2024-07-10",
              "image": {
                "height": 640,
                "url": "https://i.scdn.co/image/ab67616d0000b2737dee74002c4b00186e60af95",
                "width": 640
              }
            },
            "success": true,
            "time": 1723175172612
          }
        },
        {
          "_id": "6ZiM5cdV19vn9PrHCaKczJ",
          "count": 2,
          "details": {
            "id": "6ZiM5cdV19vn9PrHCaKczJ",
            "progress": 0.14435432425043287,
            "duration_ms": 274325,
            "playing": true,
            "name": "\u9318",
            "preview_url": "https://p.scdn.co/mp3-preview/55e88bdbe333ddb5a725a5be56dedc84319a96b3?cid=ffce38f98386483bbbee2d4831104c2b",
            "artists": [
              {
                "name": "\u5e78\u795c",
                "id": "1oM8EdalXNF4uSK5k2dzLh"
              }
            ],
            "context": {
              "external_urls": {
                "spotify": "https://open.spotify.com/playlist/2mj5XBp8jHMOMcHQL3RYjH"
              },
              "href": "https://api.spotify.com/v1/playlists/2mj5XBp8jHMOMcHQL3RYjH",
              "type": "playlist",
              "uri": "spotify:playlist:2mj5XBp8jHMOMcHQL3RYjH"
            },
            "album": {
              "name": "prayer",
              "id": "2W4yw8i2Qa4D5yDjM1hMlB",
              "release_date": "2022-02-26",
              "image": {
                "height": 640,
                "url": "https://i.scdn.co/image/ab67616d0000b273e6d293ba8dec92bcd42100b5",
                "width": 640
              }
            },
            "success": true,
            "time": 1723162026418
          }
        },
        {
          "_id": "66VlNqRXQEookzsBPjhdOX",
          "count": 2,
          "details": {
            "id": "66VlNqRXQEookzsBPjhdOX",
            "progress": 2.1879349771326306,
            "duration_ms": 160928,
            "playing": true,
            "name": "d\u00e4monisch",
            "preview_url": "https://p.scdn.co/mp3-preview/2820da368a769b90be6c8a8e0846ec887fabd80e?cid=ffce38f98386483bbbee2d4831104c2b",
            "artists": [
              {
                "name": "TUYU",
                "id": "0PHf0oiic0xAnCrRuLTtHl"
              }
            ],
            "context": {
              "external_urls": {
                "spotify": "https://open.spotify.com/playlist/2mj5XBp8jHMOMcHQL3RYjH"
              },
              "href": "https://api.spotify.com/v1/playlists/2mj5XBp8jHMOMcHQL3RYjH",
              "type": "playlist",
              "uri": "spotify:playlist:2mj5XBp8jHMOMcHQL3RYjH"
            },
            "album": {
              "name": "d\u00e4monisch",
              "id": "1J2kaWBMxFahEvtC5Vzu5i",
              "release_date": "2021-04-26",
              "image": {
                "height": 640,
                "url": "https://i.scdn.co/image/ab67616d0000b2737e2731b77e0e80e5baf2fb72",
                "width": 640
              }
            },
            "success": true,
            "time": 1723162021694
          }
        },
        {
          "_id": "7sYZ6OMUVki0Mi1yxCgRgQ",
          "count": 1,
          "details": {
            "id": "7sYZ6OMUVki0Mi1yxCgRgQ",
            "progress": 3.4789149189152226,
            "duration_ms": 263243,
            "playing": true,
            "name": "\u767d\u663c\u5922",
            "preview_url": "https://p.scdn.co/mp3-preview/2d1a8f3ace62d3f3499043d159e0e850f9b84114?cid=ffce38f98386483bbbee2d4831104c2b",
            "artists": [
              {
                "name": "\u5e78\u795c",
                "id": "1oM8EdalXNF4uSK5k2dzLh"
              }
            ],
            "context": {
              "external_urls": {
                "spotify": "https://open.spotify.com/playlist/2mj5XBp8jHMOMcHQL3RYjH"
              },
              "href": "https://api.spotify.com/v1/playlists/2mj5XBp8jHMOMcHQL3RYjH",
              "type": "playlist",
              "uri": "spotify:playlist:2mj5XBp8jHMOMcHQL3RYjH"
            },
            "album": {
              "name": "prayer",
              "id": "2W4yw8i2Qa4D5yDjM1hMlB",
              "release_date": "2022-02-26",
              "image": {
                "height": 640,
                "url": "https://i.scdn.co/image/ab67616d0000b273e6d293ba8dec92bcd42100b5",
                "width": 640
              }
            },
            "success": true,
            "time": 1723161985312
          }
        },
        {
          "_id": "0ZiO07cHvb675UDaKB1iix",
          "count": 1,
          "details": {
            "id": "0ZiO07cHvb675UDaKB1iix",
            "progress": 1.0486477292056473,
            "duration_ms": 235160,
            "playing": true,
            "name": "\u30b3\u30a4\u30ef\u30ba\u30e9\u30a4",
            "preview_url": "https://p.scdn.co/mp3-preview/b98b17a63a8ac82a55ec24f9d6d95cc655702295?cid=ffce38f98386483bbbee2d4831104c2b",
            "artists": [
              {
                "name": "Aimer",
                "id": "0bAsR2unSRpn6BQPEnNlZm"
              }
            ],
            "context": {
              "external_urls": {
                "spotify": "https://open.spotify.com/playlist/2mj5XBp8jHMOMcHQL3RYjH"
              },
              "href": "https://api.spotify.com/v1/playlists/2mj5XBp8jHMOMcHQL3RYjH",
              "type": "playlist",
              "uri": "spotify:playlist:2mj5XBp8jHMOMcHQL3RYjH"
            },
            "album": {
              "name": "Sun Dance",
              "id": "0FNWMFyb0nLCCHucsDfxmA",
              "release_date": "2019-04-09",
              "image": {
                "height": 640,
                "url": "https://i.scdn.co/image/ab67616d0000b273189f203384af534b6b269e7d",
                "width": 640
              }
            },
            "success": true,
            "time": 1723162323401
          }
        },
        {
          "_id": "5IJ7NfZbARDLEmxPgv2dmw",
          "count": 1,
          "details": {
            "id": "5IJ7NfZbARDLEmxPgv2dmw",
            "progress": 64.16791443850268,
            "duration_ms": 187000,
            "playing": true,
            "name": "\u307b\u308d\u3088\u3044",
            "preview_url": "https://p.scdn.co/mp3-preview/62d7d680c66a5e1e2b98384336d0867fc9a08517?cid=ffce38f98386483bbbee2d4831104c2b",
            "artists": [
              {
                "name": "Shion Tsuji",
                "id": "4nEJOLgBBjsWUWBMgs3IZG"
              }
            ],
            "context": {
              "external_urls": {
                "spotify": "https://open.spotify.com/playlist/2mj5XBp8jHMOMcHQL3RYjH"
              },
              "href": "https://api.spotify.com/v1/playlists/2mj5XBp8jHMOMcHQL3RYjH",
              "type": "playlist",
              "uri": "spotify:playlist:2mj5XBp8jHMOMcHQL3RYjH"
            },
            "album": {
              "name": "Oh! My Mistakes!",
              "id": "4l4fCmtGBysNPLec0ESusM",
              "release_date": "2016-12-21",
              "image": {
                "height": 640,
                "url": "https://i.scdn.co/image/ab67616d0000b273cae19d41cebf854b1f643bf9",
                "width": 640
              }
            },
            "success": true,
            "time": 1723161632356
          }
        },
        {
          "_id": "5V83biigiroB25ynkU7uJX",
          "count": 1,
          "details": {
            "id": "5V83biigiroB25ynkU7uJX",
            "progress": 0,
            "duration_ms": 193246,
            "playing": true,
            "name": "\u30b9\u30ed\u30a6\u30ea\u30fc",
            "preview_url": null,
            "artists": [
              {
                "name": "\u660e\u900f",
                "id": "71e65rSv8Dh3bfWNPQ1V1Q"
              }
            ],
            "context": {
              "external_urls": {
                "spotify": "https://open.spotify.com/playlist/2mj5XBp8jHMOMcHQL3RYjH"
              },
              "href": "https://api.spotify.com/v1/playlists/2mj5XBp8jHMOMcHQL3RYjH",
              "type": "playlist",
              "uri": "spotify:playlist:2mj5XBp8jHMOMcHQL3RYjH"
            },
            "album": {
              "name": "\u30b9\u30ed\u30a6\u30ea\u30fc",
              "id": "4SYWNHaofbcYei6BKKcOc3",
              "release_date": "2022-05-06",
              "image": {
                "height": 640,
                "url": "https://i.scdn.co/image/ab67616d0000b2735ba6fe1e84cd66abd2948a3e",
                "width": 640
              }
            },
            "success": true,
            "time": 1723162337462
          }
        },
        {
          "_id": "1zwZprYzd16KeGx8cl4Ean",
          "count": 1,
          "details": {
            "id": "1zwZprYzd16KeGx8cl4Ean",
            "progress": 0.8022462896109106,
            "duration_ms": 186975,
            "playing": true,
            "name": "Black Dilemma",
            "preview_url": "https://p.scdn.co/mp3-preview/916d5cecb63d3181fdd1507420eb0b3c1ba50af6?cid=ffce38f98386483bbbee2d4831104c2b",
            "artists": [
              {
                "name": "MOTTO MUSIC",
                "id": "69eIvKHcfYigWsgnBSv1jW"
              },
              {
                "name": "Empty old City",
                "id": "3RvUqTyR1WwQzNaGuBKnCY"
              }
            ],
            "context": {
              "external_urls": {
                "spotify": "https://open.spotify.com/collection/tracks"
              },
              "href": "https://api.spotify.com/v1/me/tracks",
              "type": "collection",
              "uri": "spotify:user:216m3lxuwmrmfde7wksjzb4pa:collection"
            },
            "album": {
              "name": "Angle.",
              "id": "57oaoVjAJxCPkXM2F60J2x",
              "release_date": "2023-04-28",
              "image": {
                "height": 640,
                "url": "https://i.scdn.co/image/ab67616d0000b2733235b8176c379e609e7cad7d",
                "width": 640
              }
            },
            "success": true,
            "time": 1723175170190
          }
        },
        {
          "_id": "4cTL5Fb8VwlpPwgRZMZS3g",
          "count": 1,
          "details": {
            "id": "4cTL5Fb8VwlpPwgRZMZS3g",
            "progress": 18.268742323990303,
            "duration_ms": 155517,
            "playing": true,
            "name": "\u98df\u866b\u690d\u7269",
            "preview_url": null,
            "artists": [
              {
                "name": "\u7406\u82bd",
                "id": "1rFELoNfdLOYWPwtrBN6zS"
              }
            ],
            "context": {
              "external_urls": {
                "spotify": "https://open.spotify.com/playlist/2mj5XBp8jHMOMcHQL3RYjH"
              },
              "href": "https://api.spotify.com/v1/playlists/2mj5XBp8jHMOMcHQL3RYjH",
              "type": "playlist",
              "uri": "spotify:playlist:2mj5XBp8jHMOMcHQL3RYjH"
            },
            "album": {
              "name": "\u98df\u866b\u690d\u7269",
              "id": "3LGrU1LbX5lzMpIvZAOubr",
              "release_date": "2020-08-12",
              "image": {
                "height": 640,
                "url": "https://i.scdn.co/image/ab67616d0000b273b711e1d0cb72367fb90b89a2",
                "width": 640
              }
            },
            "success": true,
            "time": 1723161767481
          }
        },
        {
          "_id": "7y1vLPTfjdYgRVgowFsJTW",
          "count": 1,
          "details": {
            "id": "7y1vLPTfjdYgRVgowFsJTW",
            "progress": 0.6383040935672515,
            "duration_ms": 342000,
            "playing": true,
            "name": "Alice in \u51b7\u51cd\u5eab",
            "preview_url": "https://p.scdn.co/mp3-preview/05b35d94056e3776232954c253bbe63e4d39e81d?cid=ffce38f98386483bbbee2d4831104c2b",
            "artists": [
              {
                "name": "MARY",
                "id": "08EO45FsrKqyDaVHocLjug"
              }
            ],
            "context": {
              "external_urls": {
                "spotify": "https://open.spotify.com/playlist/2mj5XBp8jHMOMcHQL3RYjH"
              },
              "href": "https://api.spotify.com/v1/playlists/2mj5XBp8jHMOMcHQL3RYjH",
              "type": "playlist",
              "uri": "spotify:playlist:2mj5XBp8jHMOMcHQL3RYjH"
            },
            "album": {
              "name": "\u5f7c\u306f\u304d\u3063\u3068\u9b54\u6cd5\u3092\u4f7f\u3046\u3002",
              "id": "0qcgUHCCNHbkv1Ej6yySyt",
              "release_date": "2017-11-02",
              "image": {
                "height": 640,
                "url": "https://i.scdn.co/image/ab67616d0000b273fc82ab470776e6f723e6c487",
                "width": 640
              }
            },
            "success": true,
            "time": 1723162332780
          }
        },
        {
          "_id": "2pq2AXsdeVacOdDP4Vn7tp",
          "count": 1,
          "details": {
            "id": "2pq2AXsdeVacOdDP4Vn7tp",
            "progress": 0.8073889580738896,
            "duration_ms": 192720,
            "playing": true,
            "name": "\u30aa\u30e9\u30c8\u30ea\u30aa",
            "preview_url": "https://p.scdn.co/mp3-preview/61797f1c63070c4864720c4440e0902689a07a78?cid=ffce38f98386483bbbee2d4831104c2b",
            "artists": [
              {
                "name": "\u6700\u7d42\u5b9a\u7406\u8ad6\u8005",
                "id": "17cHGQw4BZUHgmKQNHNJ8P"
              }
            ],
            "context": {
              "external_urls": {
                "spotify": "https://open.spotify.com/collection/tracks"
              },
              "href": "https://api.spotify.com/v1/me/tracks",
              "type": "collection",
              "uri": "spotify:user:216m3lxuwmrmfde7wksjzb4pa:collection"
            },
            "album": {
              "name": "ORATORIO",
              "id": "6zSgNsWpaZ1qBE251DLagV",
              "release_date": "2021-11-24",
              "image": {
                "height": 640,
                "url": "https://i.scdn.co/image/ab67616d0000b2736dd9e6ec81c345c2cc158cb1",
                "width": 640
              }
            },
            "success": true,
            "time": 1723175162787
          }
        },
        {
          "_id": "2sb0MPuym9pDaru5M2DHsU",
          "count": 1,
          "details": {
            "id": "2sb0MPuym9pDaru5M2DHsU",
            "progress": 99.04150292341608,
            "duration_ms": 187794,
            "playing": true,
            "name": "HELP!!",
            "preview_url": "https://p.scdn.co/mp3-preview/075bb891b856c745d715fc1faf553f112080d676?cid=ffce38f98386483bbbee2d4831104c2b",
            "artists": [
              {
                "name": "Kobo Kanaeru",
                "id": "6AjW1aE0OlIoRGdnwbHgP2"
              }
            ],
            "context": {
              "external_urls": {
                "spotify": "https://open.spotify.com/collection/tracks"
              },
              "href": "https://api.spotify.com/v1/me/tracks",
              "type": "collection",
              "uri": "spotify:user:216m3lxuwmrmfde7wksjzb4pa:collection"
            },
            "album": {
              "name": "HELP!!",
              "id": "3iIHNCs8dWlSSqXRzM00IB",
              "release_date": "2024-03-27",
              "image": {
                "height": 640,
                "url": "https://i.scdn.co/image/ab67616d0000b273e0c4007daaad3c26ce9090e9",
                "width": 640
              }
            },
            "success": true,
            "time": 1723173154324
          }
        },
        {
          "_id": "0fZ324EX3fUeAMyVXR4cDw",
          "count": 1,
          "details": {
            "id": "0fZ324EX3fUeAMyVXR4cDw",
            "progress": 6.030523898801373,
            "duration_ms": 189884,
            "playing": true,
            "name": "\u30d5\u30a9\u30cb\u30a4",
            "preview_url": null,
            "artists": [
              {
                "name": "\u97f3\u697d\u7684\u540c\u4f4d\u4f53 \u53ef\u4e0d(KAFU)",
                "id": "4nZ9ZaF0eFDMDQKgrJgsqC"
              }
            ],
            "context": {
              "external_urls": {
                "spotify": "https://open.spotify.com/playlist/2mj5XBp8jHMOMcHQL3RYjH"
              },
              "href": "https://api.spotify.com/v1/playlists/2mj5XBp8jHMOMcHQL3RYjH",
              "type": "playlist",
              "uri": "spotify:playlist:2mj5XBp8jHMOMcHQL3RYjH"
            },
            "album": {
              "name": "KAF+YOU KAFU COMPILATION ALBUM \u30b7\u30f3\u30e1\u30c8\u30ea\u30fc",
              "id": "0X48PjhhnBvjYD1lC2YxAo",
              "release_date": "2021-11-28",
              "image": {
                "height": 640,
                "url": "https://i.scdn.co/image/ab67616d0000b273b310d3db8e69d5d5099566b0",
                "width": 640
              }
            },
            "success": true,
            "time": 1723161996783
          }
        },
        {
          "_id": "0Pdq4OFBQUgMb6muejgrX3",
          "count": 1,
          "details": {
            "id": "0Pdq4OFBQUgMb6muejgrX3",
            "progress": 2.034289406281007,
            "duration_ms": 216685,
            "playing": true,
            "name": "Inu no outa",
            "preview_url": "https://p.scdn.co/mp3-preview/581a7dad15ec495a281212745692165c5166d4ed?cid=ffce38f98386483bbbee2d4831104c2b",
            "artists": [
              {
                "name": "Nanahira",
                "id": "0bkkiFN0ghGl4j9aLi3oQx"
              },
              {
                "name": "Aiobahn",
                "id": "3AMFQZ3Tt549kShRG2IBYT"
              }
            ],
            "context": {
              "external_urls": {
                "spotify": "https://open.spotify.com/playlist/2mj5XBp8jHMOMcHQL3RYjH"
              },
              "href": "https://api.spotify.com/v1/playlists/2mj5XBp8jHMOMcHQL3RYjH",
              "type": "playlist",
              "uri": "spotify:playlist:2mj5XBp8jHMOMcHQL3RYjH"
            },
            "album": {
              "name": "Inu no outa",
              "id": "50dWQWLl0wg6xD8Pn2KTp5",
              "release_date": "2022-04-01",
              "image": {
                "height": 640,
                "url": "https://i.scdn.co/image/ab67616d0000b273c22fb2ebcdfb9fc40c14d1bf",
                "width": 640
              }
            },
            "success": true,
            "time": 1723161978346
          }
        },
        {
          "_id": "0p5JKxO0pVynWVcWm3lMiP",
          "count": 1,
          "details": {
            "id": "0p5JKxO0pVynWVcWm3lMiP",
            "progress": 99.86388775312574,
            "duration_ms": 185876,
            "playing": true,
            "name": "I I I",
            "preview_url": "https://p.scdn.co/mp3-preview/f68b9446e32bb2e3315b257cbf784a452530e7aa?cid=ffce38f98386483bbbee2d4831104c2b",
            "artists": [
              {
                "name": "\u5b9d\u9418\u30de\u30ea\u30f3",
                "id": "5XaBNKQo65yYcjNA8wQPOk"
              },
              {
                "name": "Kobo Kanaeru",
                "id": "6AjW1aE0OlIoRGdnwbHgP2"
              }
            ],
            "context": {
              "external_urls": {
                "spotify": "https://open.spotify.com/collection/tracks"
              },
              "href": "https://api.spotify.com/v1/me/tracks",
              "type": "collection",
              "uri": "spotify:user:216m3lxuwmrmfde7wksjzb4pa:collection"
            },
            "album": {
              "name": "I I I",
              "id": "6khDJU0RLPOsxLWNk8HJQs",
              "release_date": "2024-05-04",
              "image": {
                "height": 640,
                "url": "https://i.scdn.co/image/ab67616d0000b27381bffc699c75f72c1f7313aa",
                "width": 640
              }
            },
            "success": true,
            "time": 1723174847408
          }
        },
        {
          "_id": "7z6qHGEKxRtwtYym2epV7l",
          "count": 1,
          "details": {
            "id": "7z6qHGEKxRtwtYym2epV7l",
            "progress": 1.4769218950309932,
            "duration_ms": 208271,
            "playing": true,
            "name": "\u8e0a",
            "preview_url": "https://p.scdn.co/mp3-preview/85ac9207475613c3de4a2b707f3c216b024ac121?cid=ffce38f98386483bbbee2d4831104c2b",
            "artists": [
              {
                "name": "Ado",
                "id": "6mEQK9m2krja6X1cfsAjfl"
              }
            ],
            "context": {
              "external_urls": {
                "spotify": "https://open.spotify.com/playlist/2mj5XBp8jHMOMcHQL3RYjH"
              },
              "href": "https://api.spotify.com/v1/playlists/2mj5XBp8jHMOMcHQL3RYjH",
              "type": "playlist",
              "uri": "spotify:playlist:2mj5XBp8jHMOMcHQL3RYjH"
            },
            "album": {
              "name": "\u8e0a",
              "id": "6jfXGkieuNnsFxi5pS3vJ2",
              "release_date": "2021-04-27",
              "image": {
                "height": 640,
                "url": "https://i.scdn.co/image/ab67616d0000b2730f7bef8299e3738350d6846e",
                "width": 640
              }
            },
            "success": true,
            "time": 1723162328082
          }
        },
        {
          "_id": "2Cnm1u2ly8QWLbt3E8rrwS",
          "count": 1,
          "details": {
            "id": "2Cnm1u2ly8QWLbt3E8rrwS",
            "progress": 0.5003641464138322,
            "duration_ms": 222438,
            "playing": true,
            "name": "\u3042\u306a\u305f\u3057\u304b\u898b\u3048\u306a\u3044\u306e",
            "preview_url": "https://p.scdn.co/mp3-preview/e0d61a33baa5cceab83f62daaab69521daaf8d9c?cid=ffce38f98386483bbbee2d4831104c2b",
            "artists": [
              {
                "name": "r-906",
                "id": "7os1UVlIK50EAaP990Z8aE"
              }
            ],
            "context": {
              "external_urls": {
                "spotify": "https://open.spotify.com/collection/tracks"
              },
              "href": "https://api.spotify.com/v1/me/tracks",
              "type": "collection",
              "uri": "spotify:user:216m3lxuwmrmfde7wksjzb4pa:collection"
            },
            "album": {
              "name": "\u3042\u306a\u305f\u3057\u304b\u898b\u3048\u306a\u3044\u306e",
              "id": "1Elhg9rcCqOWvfiFcBt6Px",
              "release_date": "2024-04-25",
              "image": {
                "height": 640,
                "url": "https://i.scdn.co/image/ab67616d0000b273ed072a82ef3678f8795dd2d6",
                "width": 640
              }
            },
            "success": true,
            "time": 1723175165215
          }
        },
        {
          "_id": "2Lphm5lQ3bOULctWRuMhJ8",
          "count": 1,
          "details": {
            "id": "2Lphm5lQ3bOULctWRuMhJ8",
            "progress": 66.81397020748182,
            "duration_ms": 198909,
            "playing": true,
            "name": "f\u016bmi zekka",
            "preview_url": "https://p.scdn.co/mp3-preview/a5095ed7f1e3b2e9b2f9249710253198abaf8307?cid=ffce38f98386483bbbee2d4831104c2b",
            "artists": [
              {
                "name": "YuNi",
                "id": "6BzlN4V17m7ogeItP4CNN5"
              }
            ],
            "context": {
              "external_urls": {
                "spotify": "https://open.spotify.com/playlist/2mj5XBp8jHMOMcHQL3RYjH"
              },
              "href": "https://api.spotify.com/v1/playlists/2mj5XBp8jHMOMcHQL3RYjH",
              "type": "playlist",
              "uri": "spotify:playlist:2mj5XBp8jHMOMcHQL3RYjH"
            },
            "album": {
              "name": "f\u016bmi zekka",
              "id": "6B2EGXqpVPapvfPFyLlwKm",
              "release_date": "2023-08-04",
              "image": {
                "height": 640,
                "url": "https://i.scdn.co/image/ab67616d0000b27337a6bd1f6051e3114fc69ae3",
                "width": 640
              }
            },
            "success": true,
            "time": 1723161796701
          }
        },
        {
          "_id": "1jWQUBQcnHh0Rtzr8Rlu4s",
          "count": 1,
          "details": {
            "id": "1jWQUBQcnHh0Rtzr8Rlu4s",
            "progress": 0.7096703848907051,
            "duration_ms": 210943,
            "playing": true,
            "name": "\u30d6\u30eb\u30fc\u30d7\u30ea\u30f3\u30c8",
            "preview_url": "https://p.scdn.co/mp3-preview/aad2cd9dd6ab27b807952cdbf1f4015db0da5680?cid=ffce38f98386483bbbee2d4831104c2b",
            "artists": [
              {
                "name": "NANAOAKARI",
                "id": "06jSjpC81wzjoUoE61Fhdn"
              }
            ],
            "context": {
              "external_urls": {
                "spotify": "https://open.spotify.com/collection/tracks"
              },
              "href": "https://api.spotify.com/v1/me/tracks",
              "type": "collection",
              "uri": "spotify:user:216m3lxuwmrmfde7wksjzb4pa:collection"
            },
            "album": {
              "name": "\u30d6\u30eb\u30fc\u30d7\u30ea\u30f3\u30c8",
              "id": "3ZM5smVHohm7YEhkZuqA7v",
              "release_date": "2024-07-13",
              "image": {
                "height": 640,
                "url": "https://i.scdn.co/image/ab67616d0000b273aa3f2562c06d20f70775bdae",
                "width": 640
              }
            },
            "success": true,
            "time": 1723175167739
          }
        },
        {
          "_id": "57d3ORRrQ1kj1HuHjtZOrW",
          "count": 1,
          "details": {
            "id": "57d3ORRrQ1kj1HuHjtZOrW",
            "progress": 4.470152829118848,
            "duration_ms": 227509,
            "playing": true,
            "name": "CAN-VERSE",
            "preview_url": "https://p.scdn.co/mp3-preview/2bde3f8ed983a268b0842d819d9c8990f8c63581?cid=ffce38f98386483bbbee2d4831104c2b",
            "artists": [
              {
                "name": "\u82b1\u8b5c",
                "id": "2c32JruIkUyfdycHmhIph4"
              },
              {
                "name": "ORESAMA",
                "id": "6kgXeMO4kd68uf4oEFHRS1"
              }
            ],
            "context": {
              "external_urls": {
                "spotify": "https://open.spotify.com/playlist/2mj5XBp8jHMOMcHQL3RYjH"
              },
              "href": "https://api.spotify.com/v1/playlists/2mj5XBp8jHMOMcHQL3RYjH",
              "type": "playlist",
              "uri": "spotify:playlist:2mj5XBp8jHMOMcHQL3RYjH"
            },
            "album": {
              "name": "CAN-VERSE",
              "id": "0nn01IQ3JoEuL7ISoHKOO5",
              "release_date": "2022-10-12",
              "image": {
                "height": 640,
                "url": "https://i.scdn.co/image/ab67616d0000b273d04b6503c2f1ef902211cbfb",
                "width": 640
              }
            },
            "success": true,
            "time": 1723162010371
          }
        },
        {
          "_id": "3OxCaZnYX1pJA7CwV5rZ9O",
          "count": 1,
          "details": {
            "id": "3OxCaZnYX1pJA7CwV5rZ9O",
            "progress": 44.73340471092077,
            "duration_ms": 280200,
            "playing": true,
            "name": "Shangri-La",
            "preview_url": "https://p.scdn.co/mp3-preview/51245a366b305e065a4fa6ce366b9aa95d1e8178?cid=ffce38f98386483bbbee2d4831104c2b",
            "artists": [
              {
                "name": "angela",
                "id": "2M1CLA7j3jwJNs1s90nzdL"
              }
            ],
            "context": {
              "external_urls": {
                "spotify": "https://open.spotify.com/artist/2M1CLA7j3jwJNs1s90nzdL"
              },
              "href": "https://api.spotify.com/v1/artists/2M1CLA7j3jwJNs1s90nzdL",
              "type": "artist",
              "uri": "spotify:artist:2M1CLA7j3jwJNs1s90nzdL"
            },
            "album": {
              "name": "I/O",
              "id": "5xeMXXALsJIvSfEDWyG0PB",
              "release_date": "2004-11-17",
              "image": {
                "height": 640,
                "url": "https://i.scdn.co/image/ab67616d0000b2736fd7669446ea1f0ffc855021",
                "width": 640
              }
            },
            "success": true,
            "time": 1723215400460
          }
        },
        {
          "_id": "6rnuGGp6hlH8cpy8soorsQ",
          "count": 1,
          "details": {
            "id": "6rnuGGp6hlH8cpy8soorsQ",
            "progress": 19.16723187364434,
            "duration_ms": 297826,
            "playing": true,
            "name": "\u660e\u65e5\u3078\u306ebrilliant road",
            "preview_url": "https://p.scdn.co/mp3-preview/ea1688532f84545988bb3b4e109dd0acf4497f93?cid=ffce38f98386483bbbee2d4831104c2b",
            "artists": [
              {
                "name": "angela",
                "id": "2M1CLA7j3jwJNs1s90nzdL"
              }
            ],
            "context": {
              "external_urls": {
                "spotify": "https://open.spotify.com/album/32dMorGN2lpQzWDEg2TVhz"
              },
              "href": "https://api.spotify.com/v1/albums/32dMorGN2lpQzWDEg2TVhz",
              "type": "album",
              "uri": "spotify:album:32dMorGN2lpQzWDEg2TVhz"
            },
            "album": {
              "name": "\u30bd\u30e9\u30ce\u30b3\u30a8",
              "id": "32dMorGN2lpQzWDEg2TVhz",
              "release_date": "2003-12-03",
              "image": {
                "height": 640,
                "url": "https://i.scdn.co/image/ab67616d0000b2735043ffec5537a49129c592b8",
                "width": 640
              }
            },
            "success": true,
            "time": 1723228340826
          }
        },
        {
          "_id": "22EHB5z2GwYNPA1wZ3LtL4",
          "count": 1,
          "details": {
            "id": "22EHB5z2GwYNPA1wZ3LtL4",
            "progress": 80.42835054498254,
            "duration_ms": 157161,
            "playing": true,
            "name": "Requiem",
            "preview_url": "https://p.scdn.co/mp3-preview/f0326da84be8133e236d62a4e5996f66dc098556?cid=ffce38f98386483bbbee2d4831104c2b",
            "artists": [
              {
                "name": "Kanaria",
                "id": "1k5LyiTCRzPjORzcgHqJxF"
              },
              {
                "name": "Hoshimachi Suisei",
                "id": "726WiFmWkohzodUxK3XjHX"
              }
            ],
            "context": {
              "external_urls": {
                "spotify": "https://open.spotify.com/collection/tracks"
              },
              "href": "https://api.spotify.com/v1/me/tracks",
              "type": "collection",
              "uri": "spotify:user:216m3lxuwmrmfde7wksjzb4pa:collection"
            },
            "album": {
              "name": "Requiem",
              "id": "1PwHrnwnlvNg8stBetjmyE",
              "release_date": "2023-04-15",
              "image": {
                "height": 640,
                "url": "https://i.scdn.co/image/ab67616d0000b27342c2ff9540f367559c0cb5c4",
                "width": 640
              }
            },
            "success": true,
            "time": 1723175035101
          }
        }
      ],
      "top_albums": [
        {
          "_id": "2W4yw8i2Qa4D5yDjM1hMlB",
          "count": 3,
          "details": {
            "name": "prayer",
            "id": "2W4yw8i2Qa4D5yDjM1hMlB",
            "release_date": "2022-02-26",
            "image": {
              "height": 640,
              "url": "https://i.scdn.co/image/ab67616d0000b273e6d293ba8dec92bcd42100b5",
              "width": 640
            }
          }
        },
        {
          "_id": "1J2kaWBMxFahEvtC5Vzu5i",
          "count": 2,
          "details": {
            "name": "d\u00e4monisch",
            "id": "1J2kaWBMxFahEvtC5Vzu5i",
            "release_date": "2021-04-26",
            "image": {
              "height": 640,
              "url": "https://i.scdn.co/image/ab67616d0000b2737e2731b77e0e80e5baf2fb72",
              "width": 640
            }
          }
        },
        {
          "_id": "5hdH3H4sjF4OoGsTyzPTLI",
          "count": 2,
          "details": {
            "name": "\u30b2\u30b7\u30e5\u30bf\u30eb\u30c8 (\u5d29\u58caRemix)",
            "id": "5hdH3H4sjF4OoGsTyzPTLI",
            "release_date": "2024-07-10",
            "image": {
              "height": 640,
              "url": "https://i.scdn.co/image/ab67616d0000b2737dee74002c4b00186e60af95",
              "width": 640
            }
          }
        },
        {
          "_id": "6B2EGXqpVPapvfPFyLlwKm",
          "count": 1,
          "details": {
            "name": "f\u016bmi zekka",
            "id": "6B2EGXqpVPapvfPFyLlwKm",
            "release_date": "2023-08-04",
            "image": {
              "height": 640,
              "url": "https://i.scdn.co/image/ab67616d0000b27337a6bd1f6051e3114fc69ae3",
              "width": 640
            }
          }
        },
        {
          "_id": "5xeMXXALsJIvSfEDWyG0PB",
          "count": 1,
          "details": {
            "name": "I/O",
            "id": "5xeMXXALsJIvSfEDWyG0PB",
            "release_date": "2004-11-17",
            "image": {
              "height": 640,
              "url": "https://i.scdn.co/image/ab67616d0000b2736fd7669446ea1f0ffc855021",
              "width": 640
            }
          }
        },
        {
          "_id": "32dMorGN2lpQzWDEg2TVhz",
          "count": 1,
          "details": {
            "name": "\u30bd\u30e9\u30ce\u30b3\u30a8",
            "id": "32dMorGN2lpQzWDEg2TVhz",
            "release_date": "2003-12-03",
            "image": {
              "height": 640,
              "url": "https://i.scdn.co/image/ab67616d0000b2735043ffec5537a49129c592b8",
              "width": 640
            }
          }
        },
        {
          "_id": "3LGrU1LbX5lzMpIvZAOubr",
          "count": 1,
          "details": {
            "name": "\u98df\u866b\u690d\u7269",
            "id": "3LGrU1LbX5lzMpIvZAOubr",
            "release_date": "2020-08-12",
            "image": {
              "height": 640,
              "url": "https://i.scdn.co/image/ab67616d0000b273b711e1d0cb72367fb90b89a2",
              "width": 640
            }
          }
        },
        {
          "_id": "50dWQWLl0wg6xD8Pn2KTp5",
          "count": 1,
          "details": {
            "name": "Inu no outa",
            "id": "50dWQWLl0wg6xD8Pn2KTp5",
            "release_date": "2022-04-01",
            "image": {
              "height": 640,
              "url": "https://i.scdn.co/image/ab67616d0000b273c22fb2ebcdfb9fc40c14d1bf",
              "width": 640
            }
          }
        },
        {
          "_id": "6khDJU0RLPOsxLWNk8HJQs",
          "count": 1,
          "details": {
            "name": "I I I",
            "id": "6khDJU0RLPOsxLWNk8HJQs",
            "release_date": "2024-05-04",
            "image": {
              "height": 640,
              "url": "https://i.scdn.co/image/ab67616d0000b27381bffc699c75f72c1f7313aa",
              "width": 640
            }
          }
        },
        {
          "_id": "0X48PjhhnBvjYD1lC2YxAo",
          "count": 1,
          "details": {
            "name": "KAF+YOU KAFU COMPILATION ALBUM \u30b7\u30f3\u30e1\u30c8\u30ea\u30fc",
            "id": "0X48PjhhnBvjYD1lC2YxAo",
            "release_date": "2021-11-28",
            "image": {
              "height": 640,
              "url": "https://i.scdn.co/image/ab67616d0000b273b310d3db8e69d5d5099566b0",
              "width": 640
            }
          }
        },
        {
          "_id": "4l4fCmtGBysNPLec0ESusM",
          "count": 1,
          "details": {
            "name": "Oh! My Mistakes!",
            "id": "4l4fCmtGBysNPLec0ESusM",
            "release_date": "2016-12-21",
            "image": {
              "height": 640,
              "url": "https://i.scdn.co/image/ab67616d0000b273cae19d41cebf854b1f643bf9",
              "width": 640
            }
          }
        },
        {
          "_id": "0nn01IQ3JoEuL7ISoHKOO5",
          "count": 1,
          "details": {
            "name": "CAN-VERSE",
            "id": "0nn01IQ3JoEuL7ISoHKOO5",
            "release_date": "2022-10-12",
            "image": {
              "height": 640,
              "url": "https://i.scdn.co/image/ab67616d0000b273d04b6503c2f1ef902211cbfb",
              "width": 640
            }
          }
        },
        {
          "_id": "1Elhg9rcCqOWvfiFcBt6Px",
          "count": 1,
          "details": {
            "name": "\u3042\u306a\u305f\u3057\u304b\u898b\u3048\u306a\u3044\u306e",
            "id": "1Elhg9rcCqOWvfiFcBt6Px",
            "release_date": "2024-04-25",
            "image": {
              "height": 640,
              "url": "https://i.scdn.co/image/ab67616d0000b273ed072a82ef3678f8795dd2d6",
              "width": 640
            }
          }
        },
        {
          "_id": "57oaoVjAJxCPkXM2F60J2x",
          "count": 1,
          "details": {
            "name": "Angle.",
            "id": "57oaoVjAJxCPkXM2F60J2x",
            "release_date": "2023-04-28",
            "image": {
              "height": 640,
              "url": "https://i.scdn.co/image/ab67616d0000b2733235b8176c379e609e7cad7d",
              "width": 640
            }
          }
        },
        {
          "_id": "6jfXGkieuNnsFxi5pS3vJ2",
          "count": 1,
          "details": {
            "name": "\u8e0a",
            "id": "6jfXGkieuNnsFxi5pS3vJ2",
            "release_date": "2021-04-27",
            "image": {
              "height": 640,
              "url": "https://i.scdn.co/image/ab67616d0000b2730f7bef8299e3738350d6846e",
              "width": 640
            }
          }
        },
        {
          "_id": "0FNWMFyb0nLCCHucsDfxmA",
          "count": 1,
          "details": {
            "name": "Sun Dance",
            "id": "0FNWMFyb0nLCCHucsDfxmA",
            "release_date": "2019-04-09",
            "image": {
              "height": 640,
              "url": "https://i.scdn.co/image/ab67616d0000b273189f203384af534b6b269e7d",
              "width": 640
            }
          }
        },
        {
          "_id": "0qcgUHCCNHbkv1Ej6yySyt",
          "count": 1,
          "details": {
            "name": "\u5f7c\u306f\u304d\u3063\u3068\u9b54\u6cd5\u3092\u4f7f\u3046\u3002",
            "id": "0qcgUHCCNHbkv1Ej6yySyt",
            "release_date": "2017-11-02",
            "image": {
              "height": 640,
              "url": "https://i.scdn.co/image/ab67616d0000b273fc82ab470776e6f723e6c487",
              "width": 640
            }
          }
        },
        {
          "_id": "4SYWNHaofbcYei6BKKcOc3",
          "count": 1,
          "details": {
            "name": "\u30b9\u30ed\u30a6\u30ea\u30fc",
            "id": "4SYWNHaofbcYei6BKKcOc3",
            "release_date": "2022-05-06",
            "image": {
              "height": 640,
              "url": "https://i.scdn.co/image/ab67616d0000b2735ba6fe1e84cd66abd2948a3e",
              "width": 640
            }
          }
        },
        {
          "_id": "1PwHrnwnlvNg8stBetjmyE",
          "count": 1,
          "details": {
            "name": "Requiem",
            "id": "1PwHrnwnlvNg8stBetjmyE",
            "release_date": "2023-04-15",
            "image": {
              "height": 640,
              "url": "https://i.scdn.co/image/ab67616d0000b27342c2ff9540f367559c0cb5c4",
              "width": 640
            }
          }
        },
        {
          "_id": "3iIHNCs8dWlSSqXRzM00IB",
          "count": 1,
          "details": {
            "name": "HELP!!",
            "id": "3iIHNCs8dWlSSqXRzM00IB",
            "release_date": "2024-03-27",
            "image": {
              "height": 640,
              "url": "https://i.scdn.co/image/ab67616d0000b273e0c4007daaad3c26ce9090e9",
              "width": 640
            }
          }
        },
        {
          "_id": "3ZM5smVHohm7YEhkZuqA7v",
          "count": 1,
          "details": {
            "name": "\u30d6\u30eb\u30fc\u30d7\u30ea\u30f3\u30c8",
            "id": "3ZM5smVHohm7YEhkZuqA7v",
            "release_date": "2024-07-13",
            "image": {
              "height": 640,
              "url": "https://i.scdn.co/image/ab67616d0000b273aa3f2562c06d20f70775bdae",
              "width": 640
            }
          }
        },
        {
          "_id": "6zSgNsWpaZ1qBE251DLagV",
          "count": 1,
          "details": {
            "name": "ORATORIO",
            "id": "6zSgNsWpaZ1qBE251DLagV",
            "release_date": "2021-11-24",
            "image": {
              "height": 640,
              "url": "https://i.scdn.co/image/ab67616d0000b2736dd9e6ec81c345c2cc158cb1",
              "width": 640
            }
          }
        }
      ],
      "top_artists": [
        {
          "_id": "2c32JruIkUyfdycHmhIph4",
          "count": 3,
          "details": {
            "name": "\u82b1\u8b5c",
            "id": "2c32JruIkUyfdycHmhIph4"
          }
        },
        {
          "_id": "1oM8EdalXNF4uSK5k2dzLh",
          "count": 3,
          "details": {
            "name": "\u5e78\u795c",
            "id": "1oM8EdalXNF4uSK5k2dzLh"
          }
        },
        {
          "_id": "6AjW1aE0OlIoRGdnwbHgP2",
          "count": 2,
          "details": {
            "name": "Kobo Kanaeru",
            "id": "6AjW1aE0OlIoRGdnwbHgP2"
          }
        },
        {
          "_id": "2M1CLA7j3jwJNs1s90nzdL",
          "count": 2,
          "details": {
            "name": "angela",
            "id": "2M1CLA7j3jwJNs1s90nzdL"
          }
        },
        {
          "_id": "0PHf0oiic0xAnCrRuLTtHl",
          "count": 2,
          "details": {
            "name": "TUYU",
            "id": "0PHf0oiic0xAnCrRuLTtHl"
          }
        },
        {
          "_id": "6lDhtdOHuApMDkvQWtDpdV",
          "count": 2,
          "details": {
            "name": "Otome",
            "id": "6lDhtdOHuApMDkvQWtDpdV"
          }
        },
        {
          "_id": "1rFELoNfdLOYWPwtrBN6zS",
          "count": 1,
          "details": {
            "name": "\u7406\u82bd",
            "id": "1rFELoNfdLOYWPwtrBN6zS"
          }
        },
        {
          "_id": "71e65rSv8Dh3bfWNPQ1V1Q",
          "count": 1,
          "details": {
            "name": "\u660e\u900f",
            "id": "71e65rSv8Dh3bfWNPQ1V1Q"
          }
        },
        {
          "_id": "5XaBNKQo65yYcjNA8wQPOk",
          "count": 1,
          "details": {
            "name": "\u5b9d\u9418\u30de\u30ea\u30f3",
            "id": "5XaBNKQo65yYcjNA8wQPOk"
          }
        },
        {
          "_id": "6kgXeMO4kd68uf4oEFHRS1",
          "count": 1,
          "details": {
            "name": "ORESAMA",
            "id": "6kgXeMO4kd68uf4oEFHRS1"
          }
        },
        {
          "_id": "1k5LyiTCRzPjORzcgHqJxF",
          "count": 1,
          "details": {
            "name": "Kanaria",
            "id": "1k5LyiTCRzPjORzcgHqJxF"
          }
        },
        {
          "_id": "17cHGQw4BZUHgmKQNHNJ8P",
          "count": 1,
          "details": {
            "name": "\u6700\u7d42\u5b9a\u7406\u8ad6\u8005",
            "id": "17cHGQw4BZUHgmKQNHNJ8P"
          }
        },
        {
          "_id": "06jSjpC81wzjoUoE61Fhdn",
          "count": 1,
          "details": {
            "name": "NANAOAKARI",
            "id": "06jSjpC81wzjoUoE61Fhdn"
          }
        },
        {
          "_id": "69eIvKHcfYigWsgnBSv1jW",
          "count": 1,
          "details": {
            "name": "MOTTO MUSIC",
            "id": "69eIvKHcfYigWsgnBSv1jW"
          }
        },
        {
          "_id": "3RvUqTyR1WwQzNaGuBKnCY",
          "count": 1,
          "details": {
            "name": "Empty old City",
            "id": "3RvUqTyR1WwQzNaGuBKnCY"
          }
        },
        {
          "_id": "3AMFQZ3Tt549kShRG2IBYT",
          "count": 1,
          "details": {
            "name": "Aiobahn",
            "id": "3AMFQZ3Tt549kShRG2IBYT"
          }
        },
        {
          "_id": "0bAsR2unSRpn6BQPEnNlZm",
          "count": 1,
          "details": {
            "name": "Aimer",
            "id": "0bAsR2unSRpn6BQPEnNlZm"
          }
        },
        {
          "_id": "726WiFmWkohzodUxK3XjHX",
          "count": 1,
          "details": {
            "name": "Hoshimachi Suisei",
            "id": "726WiFmWkohzodUxK3XjHX"
          }
        },
        {
          "_id": "4nEJOLgBBjsWUWBMgs3IZG",
          "count": 1,
          "details": {
            "name": "Shion Tsuji",
            "id": "4nEJOLgBBjsWUWBMgs3IZG"
          }
        },
        {
          "_id": "6BzlN4V17m7ogeItP4CNN5",
          "count": 1,
          "details": {
            "name": "YuNi",
            "id": "6BzlN4V17m7ogeItP4CNN5"
          }
        },
        {
          "_id": "0bkkiFN0ghGl4j9aLi3oQx",
          "count": 1,
          "details": {
            "name": "Nanahira",
            "id": "0bkkiFN0ghGl4j9aLi3oQx"
          }
        },
        {
          "_id": "7os1UVlIK50EAaP990Z8aE",
          "count": 1,
          "details": {
            "name": "r-906",
            "id": "7os1UVlIK50EAaP990Z8aE"
          }
        },
        {
          "_id": "4nZ9ZaF0eFDMDQKgrJgsqC",
          "count": 1,
          "details": {
            "name": "\u97f3\u697d\u7684\u540c\u4f4d\u4f53 \u53ef\u4e0d(KAFU)",
            "id": "4nZ9ZaF0eFDMDQKgrJgsqC"
          }
        },
        {
          "_id": "08EO45FsrKqyDaVHocLjug",
          "count": 1,
          "details": {
            "name": "MARY",
            "id": "08EO45FsrKqyDaVHocLjug"
          }
        },
        {
          "_id": "6mEQK9m2krja6X1cfsAjfl",
          "count": 1,
          "details": {
            "name": "Ado",
            "id": "6mEQK9m2krja6X1cfsAjfl"
          }
        }
      ],
      "total_listen_time": [
        {
          "_id": null,
          "listened_ms": 1489665.0
        }
      ]
    }
  }
}